gluex/jupyroot/__init__.py
gluex/jupyroot/hddmview.py
gluex/jupyroot/treeview.py
gluex_jupyroot-1.0.20.dist-info/licenses/LICENSE
gluex_jupyroot-1.0.20.dist-info/METADATA
gluex_jupyroot-1.0.20.dist-info/WHEEL
gluex_jupyroot-1.0.20.dist-info/top_level.txt
gluex_jupyroot-1.0.20.dist-info/RECORD
