Metadata-Version: 2.4
Name: gluex.jupyroot
Version: 1.0.20
Summary: Automate common data analysis and visualization tasks using the CERN pyroot library in a jupyter notebook.
Home-page: https://github.com/rjones30/jupyroot
Author: Richard Jones
Author-email: richard.t.jones@uconn.edu
Classifier: Programming Language :: Python :: 3
Classifier: License :: OSI Approved :: GNU General Public License v3 or later (GPLv3+)
Classifier: Operating System :: OS Independent
Requires-Python: >=3.9
License-File: LICENSE
Dynamic: author
Dynamic: author-email
Dynamic: classifier
Dynamic: description
Dynamic: description-content-type
Dynamic: home-page
Dynamic: license-file
Dynamic: requires-python
Dynamic: summary
